[
    {
        "name": "id",
        "dbType": "bigInteger,true,true",
        "htmlType": "number",
        "validations": "",
        "searchable": false,
        "fillable": false,
        "primary": true,
        "inForm": false,
        "inIndex": false,
        "inView": false
    },
    {
        "name": "busNumber",
        "dbType": "integer,false,true",
        "htmlType": "number",
        "validations": "nullable|nullable|nullable",
        "searchable": true,
        "fillable": true,
        "primary": false,
        "inForm": true,
        "inIndex": true,
        "inView": true
    },
    {
        "name": "deviceAddress",
        "dbType": "integer,false,true",
        "htmlType": "number",
        "validations": "nullable|nullable|nullable",
        "searchable": true,
        "fillable": true,
        "primary": false,
        "inForm": true,
        "inIndex": true,
        "inView": true
    },
    {
        "name": "vendorId",
        "dbType": "integer,false,true",
        "htmlType": "number",
        "validations": "nullable|nullable|nullable",
        "searchable": true,
        "fillable": true,
        "primary": false,
        "inForm": true,
        "inIndex": true,
        "inView": true
    },
    {
        "name": "productId",
        "dbType": "integer,false,true",
        "htmlType": "number",
        "validations": "nullable|nullable|nullable",
        "searchable": true,
        "fillable": true,
        "primary": false,
        "inForm": true,
        "inIndex": true,
        "inView": true
    },
    {
        "name": "macAddress",
        "dbType": "string",
        "htmlType": "text",
        "validations": "nullable|string|max:255|nullable|string|max:255|nullable|string|max:255",
        "searchable": true,
        "fillable": true,
        "primary": false,
        "inForm": true,
        "inIndex": true,
        "inView": true
    },
    {
        "name": "created_at",
        "dbType": "datetime",
        "htmlType": "date",
        "validations": "nullable|nullable|nullable",
        "searchable": false,
        "fillable": false,
        "primary": false,
        "inForm": false,
        "inIndex": false,
        "inView": false
    },
    {
        "name": "updated_at",
        "dbType": "datetime",
        "htmlType": "date",
        "validations": "nullable|nullable|nullable",
        "searchable": false,
        "fillable": false,
        "primary": false,
        "inForm": false,
        "inIndex": false,
        "inView": false
    }
]